CHANGES.md
bovine_store/__init__.py
bovine_store/__main__.py
bovine_store/actor/__init__.py
bovine_store/actor/bovine_store_actor.py
bovine_store/actor/register.py
bovine_store/actor/test_bovine_application_actor.py
bovine_store/actor/test_bovine_store_actor.py
bovine_store/actor/test_register.py
bovine_store/config.py
bovine_store/models.py
bovine_store/store/__init__.py
bovine_store/store/collection.py
bovine_store/store/remote.py
bovine_store/store/retrieve_object.py
bovine_store/store/store.py
bovine_store/store/test_application_actor_data.py
bovine_store/store/test_collection.py
bovine_store/store/test_retrieve_object.py
bovine_store/store/test_store.py
bovine_store/store/test_store_remote.py
bovine_store/store/test_utils.py
bovine_store/store/utils.py
bovine_store/test_bovine_admin_store.py
bovine_store/test_store.py
bovine_store/types.py
bovine_store/utils/__init__.py
bovine_store/utils/cli.py
bovine_store/utils/permissions.py
bovine_store/utils/test.py
bovine_store/utils/test_cli.py
bovine_store/utils/test_permissions.py
bovine_store/utils/test_summary.py
bovine_store/utils/test_test.py
bovine_store-0.5.19.dist-info/METADATA
bovine_store-0.5.19.dist-info/WHEEL
bovine_store-0.5.19.dist-info/RECORD
