Metadata-Version: 2.1
Name: bovine-store
Version: 0.5.19
Summary: Store for ActivityPub activities, actors and objects
Home-page: https://codeberg.org/bovine/bovine
License: MIT
Author: Helge
Author-email: helge.krueger@gmail.com
Requires-Python: >=3.11,<4.0
Classifier: Intended Audience :: Developers
Classifier: License :: OSI Approved :: MIT License
Classifier: Programming Language :: Python :: 3
Classifier: Programming Language :: Python :: 3.11
Classifier: Programming Language :: Python :: 3.11
Classifier: Programming Language :: Python :: 3.12
Classifier: Topic :: Communications
Classifier: Topic :: Software Development :: Libraries :: Python Modules
Requires-Dist: bovine (>=0.5.19,<0.6.0)
Requires-Dist: tortoise-orm[asyncpg] (>=0.21.0,<0.22.0)
Project-URL: Documentation, https://bovine-store.readthedocs.io/en/latest/
Project-URL: Repository, https://codeberg.org/bovine/bovine
